client/__init__.py
client/add_contact.py
client/delete_contact.py
client/main_window.py
client/main_window_conv.py
client/my_client_base.py
client/start_dialog.py
client/transport.py
common/__init__.py
common/decorator.py
common/descriptor.py
common/metaclass.py
common/utils.py
common/variables.py
logs/__init__.py
logs/client_log_config.py
unitest/__init__.py
unitest/test_client.py
unitest/test_utils.py
message_client_unfun-0.8.7.dist-info/METADATA
message_client_unfun-0.8.7.dist-info/WHEEL
message_client_unfun-0.8.7.dist-info/top_level.txt
message_client_unfun-0.8.7.dist-info/RECORD
